jetson_cli/__init__.py
jetson_cli/cli.py
jetson_cli/utils.py
jetson_cli/sdk/__init__.py
jetson_cli/sdk/docker.py
jetson_cli/sdk/gui.py
jetson_cli/sdk/power.py
jetson_cli/sdk/storage.py
jetson_cli/sdk/system.py
jetson_cli-0.7.0.dist-info/licenses/LICENSE
jetson_cli-0.7.0.dist-info/METADATA
jetson_cli-0.7.0.dist-info/WHEEL
jetson_cli-0.7.0.dist-info/entry_points.txt
jetson_cli-0.7.0.dist-info/top_level.txt
jetson_cli-0.7.0.dist-info/RECORD
