Metadata-Version: 2.4
Name: jetson-cli
Version: 0.7.0
Summary: Command-line interface for NVIDIA Jetson setup and configuration
Home-page: https://github.com/your-org/jetson-setup
Author: Jetson Setup Team
Author-email: Jetson Setup Team <support@jetson-setup.com>
License: MIT
Project-URL: Homepage, https://github.com/your-org/jetson-setup
Project-URL: Documentation, https://github.com/your-org/jetson-setup/blob/main/README.md
Project-URL: Repository, https://github.com/your-org/jetson-setup.git
Project-URL: Bug Reports, https://github.com/your-org/jetson-setup/issues
Keywords: jetson,nvidia,embedded,ai,ml,docker,containers,setup
Classifier: Development Status :: 4 - Beta
Classifier: Environment :: Console
Classifier: Intended Audience :: Developers
Classifier: Intended Audience :: System Administrators
Classifier: License :: OSI Approved :: MIT License
Classifier: Operating System :: POSIX :: Linux
Classifier: Programming Language :: Python :: 3
Classifier: Programming Language :: Python :: 3.8
Classifier: Programming Language :: Python :: 3.9
Classifier: Programming Language :: Python :: 3.10
Classifier: Programming Language :: Python :: 3.11
Classifier: Programming Language :: Python :: 3.12
Classifier: Topic :: System :: Systems Administration
Classifier: Topic :: Software Development :: Libraries :: Python Modules
Classifier: Topic :: Utilities
Requires-Python: >=3.8
License-File: LICENSE
Requires-Dist: click>=8.0.0
Requires-Dist: pyyaml>=6.0
Requires-Dist: tabulate>=0.9.0
Requires-Dist: packaging>=20.0
Requires-Dist: psutil>=5.8.0
Requires-Dist: rich>=12.0.0
Provides-Extra: dev
Requires-Dist: pytest>=6.0; extra == "dev"
Requires-Dist: pytest-cov>=2.0; extra == "dev"
Requires-Dist: black>=22.0; extra == "dev"
Requires-Dist: flake8>=4.0; extra == "dev"
Requires-Dist: isort>=5.0; extra == "dev"
Requires-Dist: bump2version>=1.0; extra == "dev"
Dynamic: author
Dynamic: home-page
Dynamic: license-file
Dynamic: requires-python
